petfacts/__init__.py
petfacts/petfacts.py
petfacts-1.1.1.dist-info/LICENSE
petfacts-1.1.1.dist-info/METADATA
petfacts-1.1.1.dist-info/WHEEL
petfacts-1.1.1.dist-info/entry_points.txt
petfacts-1.1.1.dist-info/top_level.txt
petfacts-1.1.1.dist-info/RECORD
