Metadata-Version: 2.1
Name: petfacts
Version: 1.1.1
Summary: A simple program for displaying cat or dog facts.
Home-page: https://github.com/CodeCanna/petfacts
Author: Mark Allen Waid Jr
Author-email: codecannamw@gmail.com
License: : OSI Approved :: MIT License Operating System :: OS Independent
Platform: UNKNOWN
Classifier: Programming Language :: Python :: 3
Requires-Python: >=3.6
License-File: LICENSE
